discord_ansi/__init__.py
discord_ansi-1.2.dist-info/LICENSE
discord_ansi-1.2.dist-info/METADATA
discord_ansi-1.2.dist-info/WHEEL
discord_ansi-1.2.dist-info/top_level.txt
discord_ansi-1.2.dist-info/RECORD
