Metadata-Version: 2.1
Name: discord-ansi
Version: 1.2
Summary: Discord messages with ANSI (message builder + ANSI Art)
Author-email: GEOEGII555 <geoegii2001555@gmail.com>, "GEOEGII555 (Alternative email)" <webmaster@geoegii555.eu.org>
Classifier: Programming Language :: Python :: 3
Classifier: License :: OSI Approved :: MIT License
Classifier: Operating System :: OS Independent
Requires-Python: >=3.7
License-File: LICENSE
Requires-Dist: setuptools
Requires-Dist: numpy
